__init__.py
gtmx/__init__.py
gtmx/gtm_base.py
gtmx/gtmtt.py
gtmx/bokeh_app/__init__.py
gtmx/bokeh_app/main.py
GTMX-0.0.4.dist-info/LICENSE
GTMX-0.0.4.dist-info/METADATA
GTMX-0.0.4.dist-info/WHEEL
GTMX-0.0.4.dist-info/top_level.txt
GTMX-0.0.4.dist-info/RECORD
