Metadata-Version: 2.1
Name: GTMX
Version: 0.0.4
Summary: A Python package for Generative Topographic Mapping (GTM)
Home-page: https://github.com/innovationb1ue/GTMX
License-File: LICENSE
Requires-Dist: numpy
Requires-Dist: scipy
Requires-Dist: scikit-learn
Requires-Dist: matplotlib
Requires-Dist: bokeh
Requires-Dist: pandas
